LICENSE
MANIFEST.in
setup.py
cpjson/cpjson.py
cpjson.egg-info/PKG-INFO
cpjson.egg-info/SOURCES.txt
cpjson.egg-info/dependency_links.txt
cpjson.egg-info/top_level.txt
cpjson/version/__init__.py
cpjson/version/_version.py
cpjson/version/__pycache__/__init__.cpython-311.pyc
cpjson/version/__pycache__/_version.cpython-311.pyc