Metadata-Version: 2.4
Name: cpjson
Version: 4.7.5
Summary: cpjson
Home-page: https://github.com/monsur/jsoncompare
Download-URL: https://github.com/monsur/jsoncompare
Author: Monsur Hossain
Author-email: monsur.hossain@zssolutionsllc.net
Project-URL: Documentation, https://github.com/monsur/jsoncompare
License-File: LICENSE
Dynamic: author
Dynamic: author-email
Dynamic: description
Dynamic: description-content-type
Dynamic: download-url
Dynamic: home-page
Dynamic: license-file
Dynamic: project-url
Dynamic: summary
